README.rst
ledtop.py
setup.py
ledtop.egg-info/PKG-INFO
ledtop.egg-info/SOURCES.txt
ledtop.egg-info/dependency_links.txt
ledtop.egg-info/requires.txt
ledtop.egg-info/top_level.txt