Metadata-Version: 1.1
Name: ledtop
Version: 1.0.1
Summary: Like htop (CPU and memory usage), but for your case LEDs.
Home-page: https://github.com/keredson/ledtop
Author: Derek Anderson
Author-email: public@kered.org
License: UNKNOWN
Platform: UNKNOWN
Classifier: Development Status :: 4 - Beta
Classifier: Intended Audience :: Developers
Classifier: License :: OSI Approved :: GNU Lesser General Public License v3 (LGPLv3)
Classifier: Operating System :: OS Independent
Classifier: Programming Language :: Python
Classifier: Programming Language :: Python :: 3
